{
  "format": "animayte-rive-build/1",
  "generatedFrom": [
    "lib/expressions.mjs",
    "lib/anim/manifest.mjs",
    "lib/rive/contract.mjs"
  ],
  "artboard": "Pet",
  "stateMachine": "animayte",
  "inputs": [
    {
      "name": "mood",
      "kind": "number",
      "default": 0,
      "doc": "expression index 0..7 (see MOODS) — the sticky feeling"
    },
    {
      "name": "fullness",
      "kind": "number",
      "default": 0,
      "doc": "context window 0..100 → body swell + cool \"tired\" tint"
    },
    {
      "name": "tool",
      "kind": "number",
      "default": 0,
      "doc": "active tool category 0..9 (see TOOLS); 0 = none → tool gag pose"
    },
    {
      "name": "birds",
      "kind": "number",
      "default": 0,
      "doc": "orbiting sub-agents 0..5"
    },
    {
      "name": "moodLevel",
      "kind": "number",
      "default": 0,
      "doc": "slow mood drift -100..100 (stressed..up)"
    },
    {
      "name": "sleeping",
      "kind": "boolean",
      "default": false,
      "doc": "session ended → curl down, Z's"
    },
    {
      "name": "reduceMotion",
      "kind": "boolean",
      "default": false,
      "doc": "prefers-reduced-motion → dampen movement"
    },
    {
      "name": "react",
      "kind": "trigger",
      "doc": "generic emphasis bounce (happy / oops)"
    },
    {
      "name": "win",
      "kind": "trigger",
      "doc": "big celebration (excited) — confetti, star eyes"
    },
    {
      "name": "error",
      "kind": "trigger",
      "doc": "flinch then recover (sad / tool error)"
    },
    {
      "name": "compact",
      "kind": "trigger",
      "doc": "/compact relief: big inhale → exhale, steam from ears"
    },
    {
      "name": "wake",
      "kind": "trigger",
      "doc": "wake from sleep — stretch, blink awake"
    }
  ],
  "moods": [
    {
      "index": 0,
      "id": "neutral"
    },
    {
      "index": 1,
      "id": "thinking"
    },
    {
      "index": 2,
      "id": "happy"
    },
    {
      "index": 3,
      "id": "excited"
    },
    {
      "index": 4,
      "id": "oops"
    },
    {
      "index": 5,
      "id": "embarrassed"
    },
    {
      "index": 6,
      "id": "sad"
    },
    {
      "index": 7,
      "id": "sleepy"
    }
  ],
  "tools": [
    {
      "index": 0,
      "id": "none"
    },
    {
      "index": 1,
      "id": "read"
    },
    {
      "index": 2,
      "id": "search"
    },
    {
      "index": 3,
      "id": "edit"
    },
    {
      "index": 4,
      "id": "run"
    },
    {
      "index": 5,
      "id": "test"
    },
    {
      "index": 6,
      "id": "install"
    },
    {
      "index": 7,
      "id": "git"
    },
    {
      "index": 8,
      "id": "fetch"
    },
    {
      "index": 9,
      "id": "plan"
    }
  ],
  "palettes": {
    "calm": {
      "shadowCool": "#1E4D3B",
      "shadow": "#2E7D4F",
      "base": "#5BC661",
      "highlight": "#9BE86A",
      "rim": "#E8FBB0",
      "outline": "#16352B",
      "halo": "#FFFFFF4D",
      "dropShadow": "#10231C59",
      "eyeDark": "#16352B",
      "catchlight": "#F2FBE9",
      "blush": "#F6757A"
    },
    "tired": {
      "shadowCool": "#1B3A47",
      "shadow": "#2C5E6E",
      "base": "#4FA6B0",
      "highlight": "#7FCFCB",
      "rim": "#CFEFE6",
      "outline": "#15303B",
      "halo": "#FFFFFF40",
      "dropShadow": "#0E1F2659",
      "eyeDark": "#15303B",
      "catchlight": "#EAF7F4",
      "blush": "#E58BA0"
    },
    "error": {
      "shadowCool": "#5A1E22",
      "shadow": "#8E2C30",
      "base": "#E04A4A",
      "highlight": "#F58A6A",
      "rim": "#FDE0C0",
      "outline": "#3A1416",
      "halo": "#FFFFFF4D",
      "dropShadow": "#2A0E1059",
      "eyeDark": "#3A1416",
      "catchlight": "#FFF0E8",
      "blush": "#FF9BA0"
    }
  },
  "accentColors": {
    "warm": "#FEE761",
    "alert": "#E43B44",
    "neutral": "#3A4466",
    "sweat": "#7DC6FF",
    "white": "#FFFFFF"
  },
  "expressions": {
    "0": {
      "id": "neutral",
      "eyes": "dots",
      "mouth": "slight_smile",
      "apple": "🙂",
      "meaning": "idle, waiting, calm — nothing notable happening"
    },
    "1": {
      "id": "thinking",
      "eyes": "look_up",
      "mouth": "flat_skew",
      "brows": "one_raised",
      "apple": "🤔",
      "meaning": "working, investigating, considering, reading"
    },
    "2": {
      "id": "happy",
      "eyes": "happy_arc",
      "mouth": "open_smile",
      "accents": [
        "blush"
      ],
      "apple": "😄",
      "meaning": "success — it works, tests pass, a good result"
    },
    "3": {
      "id": "excited",
      "eyes": "stars",
      "mouth": "big_grin",
      "accents": [
        "blush"
      ],
      "apple": "🤩",
      "meaning": "a big win, breakthrough, or amazing result"
    },
    "4": {
      "id": "oops",
      "eyes": "open",
      "mouth": "awkward",
      "brows": "worried",
      "accents": [
        "sweat"
      ],
      "apple": "😅",
      "meaning": "a small slip / my mistake — sheepish but recoverable"
    },
    "5": {
      "id": "embarrassed",
      "eyes": "wide",
      "mouth": "small",
      "accents": [
        "flush"
      ],
      "apple": "😳",
      "meaning": "shame / embarrassment — flushed, mortified, deeper than a slip"
    },
    "6": {
      "id": "sad",
      "eyes": "open",
      "mouth": "frown",
      "brows": "sad",
      "apple": "😟",
      "meaning": "bad news, a negative finding, or an error (not the pet's own fault)"
    },
    "7": {
      "id": "sleepy",
      "eyes": "closed",
      "mouth": "small",
      "accents": [
        "zzz"
      ],
      "apple": "😴",
      "meaning": "context window full, a long session, or resting"
    }
  },
  "clips": {
    "idle": {
      "loop": true,
      "frames": [
        {
          "dur": 460,
          "cell": 0
        },
        {
          "dur": 460,
          "cell": 1
        },
        {
          "dur": 460,
          "cell": 2
        },
        {
          "dur": 460,
          "cell": 1
        }
      ],
      "tracks": {
        "body": [
          {
            "t": 0,
            "sy": 1,
            "ty": 0
          },
          {
            "t": 0.5,
            "sy": 1.03,
            "ty": -1,
            "ease": "easeInOutSine"
          },
          {
            "t": 1,
            "sy": 1,
            "ty": 0,
            "ease": "easeInOutSine"
          }
        ]
      }
    },
    "blink": {
      "loop": false,
      "frames": [
        {
          "dur": 110,
          "cell": 3
        }
      ]
    },
    "react": {
      "loop": false,
      "frames": [
        {
          "dur": 80,
          "cell": 0
        },
        {
          "dur": 110,
          "cell": 1
        },
        {
          "dur": 140,
          "cell": 2
        },
        {
          "dur": 160,
          "cell": 1
        }
      ],
      "tracks": {
        "body": [
          {
            "t": 0,
            "sy": 1
          },
          {
            "t": 0.2,
            "sy": 0.88,
            "ease": "easeOutQuad"
          },
          {
            "t": 0.5,
            "sy": 1.16,
            "ease": "easeOutBack"
          },
          {
            "t": 1,
            "sy": 1,
            "ease": "easeOutBounce"
          }
        ]
      }
    },
    "sway": {
      "loop": false,
      "frames": [
        {
          "dur": 230,
          "cell": 0
        },
        {
          "dur": 230,
          "cell": 1
        },
        {
          "dur": 230,
          "cell": 2
        },
        {
          "dur": 230,
          "cell": 1
        }
      ],
      "tracks": {
        "body": [
          {
            "t": 0,
            "tx": 0,
            "rot": 0
          },
          {
            "t": 0.3,
            "tx": -3,
            "rot": -0.05,
            "ease": "easeInOutSine"
          },
          {
            "t": 0.7,
            "tx": 3,
            "rot": 0.05,
            "ease": "easeInOutSine"
          },
          {
            "t": 1,
            "tx": 0,
            "rot": 0,
            "ease": "easeInOutSine"
          }
        ]
      }
    },
    "stretch": {
      "loop": false,
      "frames": [
        {
          "dur": 260,
          "cell": 1
        },
        {
          "dur": 300,
          "cell": 2
        },
        {
          "dur": 300,
          "cell": 2
        },
        {
          "dur": 240,
          "cell": 1
        }
      ],
      "tracks": {
        "body": [
          {
            "t": 0,
            "sy": 1
          },
          {
            "t": 0.45,
            "sy": 1.12,
            "ty": -2,
            "ease": "easeOutQuad"
          },
          {
            "t": 1,
            "sy": 1,
            "ty": 0,
            "ease": "easeInOutSine"
          }
        ]
      }
    },
    "bounce": {
      "loop": false,
      "frames": [
        {
          "dur": 120,
          "cell": 0
        },
        {
          "dur": 150,
          "cell": 2
        },
        {
          "dur": 150,
          "cell": 1
        },
        {
          "dur": 140,
          "cell": 0
        }
      ],
      "tracks": {
        "body": [
          {
            "t": 0,
            "sy": 1,
            "ty": 0
          },
          {
            "t": 0.2,
            "sy": 0.9,
            "ease": "easeOutQuad"
          },
          {
            "t": 0.5,
            "sy": 1.08,
            "ty": -7,
            "ease": "easeOutQuad"
          },
          {
            "t": 1,
            "sy": 1,
            "ty": 0,
            "ease": "easeOutBounce"
          }
        ]
      }
    },
    "doze": {
      "loop": true,
      "frames": [
        {
          "dur": 900,
          "cell": 3
        },
        {
          "dur": 900,
          "cell": 3
        }
      ],
      "tracks": {
        "body": [
          {
            "t": 0,
            "sy": 1,
            "ty": 0
          },
          {
            "t": 0.5,
            "sy": 0.97,
            "ty": 1,
            "ease": "easeInOutSine"
          },
          {
            "t": 1,
            "sy": 1,
            "ty": 0,
            "ease": "easeInOutSine"
          }
        ]
      }
    },
    "reading": {
      "loop": true,
      "frames": [
        {
          "dur": 380,
          "cell": 0
        },
        {
          "dur": 380,
          "cell": 1
        },
        {
          "dur": 380,
          "cell": 2
        },
        {
          "dur": 380,
          "cell": 1
        }
      ],
      "tracks": {
        "body": [
          {
            "t": 0,
            "ty": 2,
            "tx": -1
          },
          {
            "t": 0.5,
            "ty": 3,
            "tx": 1,
            "ease": "easeInOutSine"
          },
          {
            "t": 1,
            "ty": 2,
            "tx": -1,
            "ease": "easeInOutSine"
          }
        ]
      }
    },
    "searching": {
      "loop": true,
      "frames": [
        {
          "dur": 300,
          "cell": 0
        },
        {
          "dur": 300,
          "cell": 1
        },
        {
          "dur": 300,
          "cell": 2
        },
        {
          "dur": 300,
          "cell": 1
        }
      ],
      "tracks": {
        "body": [
          {
            "t": 0,
            "tx": -3,
            "rot": -0.05
          },
          {
            "t": 0.5,
            "tx": 3,
            "rot": 0.05,
            "ease": "easeInOutSine"
          },
          {
            "t": 1,
            "tx": -3,
            "rot": -0.05,
            "ease": "easeInOutSine"
          }
        ]
      }
    },
    "writing": {
      "loop": true,
      "frames": [
        {
          "dur": 140,
          "cell": 0
        },
        {
          "dur": 140,
          "cell": 1
        },
        {
          "dur": 140,
          "cell": 2
        },
        {
          "dur": 140,
          "cell": 1
        }
      ],
      "tracks": {
        "body": [
          {
            "t": 0,
            "ty": 0
          },
          {
            "t": 0.25,
            "ty": 1.6,
            "ease": "easeInOutSine"
          },
          {
            "t": 0.5,
            "ty": 0,
            "ease": "easeInOutSine"
          },
          {
            "t": 0.75,
            "ty": 1.6,
            "ease": "easeInOutSine"
          },
          {
            "t": 1,
            "ty": 0,
            "ease": "easeInOutSine"
          }
        ]
      }
    },
    "running": {
      "loop": true,
      "frames": [
        {
          "dur": 90,
          "cell": 0
        },
        {
          "dur": 90,
          "cell": 2
        },
        {
          "dur": 90,
          "cell": 1
        },
        {
          "dur": 90,
          "cell": 0
        }
      ],
      "tracks": {
        "body": [
          {
            "t": 0,
            "ty": 0,
            "tx": 0
          },
          {
            "t": 0.25,
            "ty": -3,
            "tx": -1,
            "ease": "easeOutQuad"
          },
          {
            "t": 0.5,
            "ty": 0,
            "tx": 0,
            "ease": "easeInQuad"
          },
          {
            "t": 0.75,
            "ty": -3,
            "tx": 1,
            "ease": "easeOutQuad"
          },
          {
            "t": 1,
            "ty": 0,
            "tx": 0,
            "ease": "easeInQuad"
          }
        ]
      }
    },
    "installing": {
      "loop": true,
      "frames": [
        {
          "dur": 300,
          "cell": 0
        },
        {
          "dur": 300,
          "cell": 1
        },
        {
          "dur": 300,
          "cell": 2
        },
        {
          "dur": 300,
          "cell": 1
        }
      ],
      "tracks": {
        "body": [
          {
            "t": 0,
            "tx": 0
          },
          {
            "t": 0.5,
            "tx": 1,
            "ease": "easeInOutSine"
          },
          {
            "t": 1,
            "tx": 0,
            "ease": "easeInOutSine"
          }
        ]
      }
    },
    "asking": {
      "loop": true,
      "frames": [
        {
          "dur": 420,
          "cell": 0
        },
        {
          "dur": 420,
          "cell": 1
        },
        {
          "dur": 420,
          "cell": 2
        },
        {
          "dur": 420,
          "cell": 1
        }
      ],
      "tracks": {
        "body": [
          {
            "t": 0,
            "rot": 0,
            "tx": 0
          },
          {
            "t": 0.4,
            "rot": 0.11,
            "tx": 1,
            "ease": "easeOutQuad"
          },
          {
            "t": 1,
            "rot": 0.11,
            "tx": 1,
            "ease": "easeInOutSine"
          }
        ]
      }
    },
    "waiting": {
      "loop": true,
      "frames": [
        {
          "dur": 500,
          "cell": 0
        },
        {
          "dur": 500,
          "cell": 1
        },
        {
          "dur": 500,
          "cell": 2
        },
        {
          "dur": 500,
          "cell": 1
        }
      ],
      "tracks": {
        "body": [
          {
            "t": 0,
            "tx": 0
          },
          {
            "t": 0.5,
            "tx": -1,
            "ease": "easeInOutSine"
          },
          {
            "t": 1,
            "tx": 0,
            "ease": "easeInOutSine"
          }
        ]
      }
    },
    "testing": {
      "loop": true,
      "frames": [
        {
          "dur": 150,
          "cell": 0
        },
        {
          "dur": 150,
          "cell": 1
        }
      ],
      "tracks": {
        "body": [
          {
            "t": 0,
            "tx": -1
          },
          {
            "t": 0.5,
            "tx": 1,
            "ease": "easeInOutSine"
          },
          {
            "t": 1,
            "tx": -1,
            "ease": "easeInOutSine"
          }
        ]
      }
    },
    "committing": {
      "loop": false,
      "frames": [
        {
          "dur": 110,
          "cell": 0
        },
        {
          "dur": 130,
          "cell": 2
        },
        {
          "dur": 170,
          "cell": 1
        }
      ],
      "tracks": {
        "body": [
          {
            "t": 0,
            "sy": 1,
            "ty": 0
          },
          {
            "t": 0.3,
            "sy": 0.84,
            "ty": 3,
            "ease": "easeOutQuad"
          },
          {
            "t": 1,
            "sy": 1,
            "ty": 0,
            "ease": "easeOutBounce"
          }
        ]
      }
    },
    "fetching": {
      "loop": true,
      "frames": [
        {
          "dur": 360,
          "cell": 0
        },
        {
          "dur": 360,
          "cell": 1
        },
        {
          "dur": 360,
          "cell": 2
        },
        {
          "dur": 360,
          "cell": 1
        }
      ],
      "tracks": {
        "body": [
          {
            "t": 0,
            "rot": -0.04,
            "ty": -1
          },
          {
            "t": 0.5,
            "rot": 0.04,
            "ty": -2,
            "ease": "easeInOutSine"
          },
          {
            "t": 1,
            "rot": -0.04,
            "ty": -1,
            "ease": "easeInOutSine"
          }
        ]
      }
    },
    "planning": {
      "loop": true,
      "frames": [
        {
          "dur": 280,
          "cell": 0
        },
        {
          "dur": 280,
          "cell": 1
        },
        {
          "dur": 280,
          "cell": 2
        },
        {
          "dur": 280,
          "cell": 1
        }
      ],
      "tracks": {
        "body": [
          {
            "t": 0,
            "ty": 0
          },
          {
            "t": 0.5,
            "ty": 2,
            "ease": "easeInOutSine"
          },
          {
            "t": 1,
            "ty": 0,
            "ease": "easeInOutSine"
          }
        ]
      }
    }
  },
  "props": {
    "glasses": {
      "cell": 0,
      "anchor": [
        0.5,
        0.42
      ],
      "pop": 2
    },
    "magnifier": {
      "cell": 1,
      "anchor": [
        0.72,
        0.5
      ],
      "pop": 2
    },
    "pencil": {
      "cell": 2,
      "anchor": [
        0.74,
        0.56
      ],
      "pop": 2
    },
    "book": {
      "cell": 3,
      "anchor": [
        0.72,
        0.52
      ],
      "pop": 2
    },
    "exclaim": {
      "cell": 4,
      "anchor": [
        0.8,
        0.14
      ],
      "pop": 2
    },
    "question": {
      "cell": 5,
      "anchor": [
        0.82,
        0.12
      ],
      "pop": 2
    },
    "ellipsis": {
      "cell": 6,
      "anchor": [
        0.84,
        0.18
      ],
      "pop": 2
    },
    "sparkle": {
      "cell": 7,
      "anchor": [
        0.24,
        0.16
      ],
      "pop": 2
    },
    "idea": {
      "cell": 8,
      "anchor": [
        0.5,
        0.04
      ],
      "pop": 2
    },
    "heart": {
      "cell": 9,
      "anchor": [
        0.76,
        0.14
      ],
      "pop": 2
    },
    "check": {
      "cell": 10,
      "anchor": [
        0.78,
        0.16
      ],
      "pop": 2
    },
    "zzz": {
      "cell": 11,
      "anchor": [
        0.74,
        0.1
      ],
      "pop": 2
    },
    "steam": {
      "cell": 12,
      "anchor": [
        0.5,
        0.06
      ],
      "pop": 2
    },
    "dust": {
      "cell": 13,
      "anchor": [
        0.5,
        0.95
      ],
      "pop": 2
    },
    "telescope": {
      "cell": 14,
      "anchor": [
        0.76,
        0.12
      ],
      "pop": 2
    },
    "checklist": {
      "cell": 15,
      "anchor": [
        0.74,
        0.5
      ],
      "pop": 2
    }
  },
  "reactions": {
    "Reading": {
      "clip": "reading",
      "expression": "thinking",
      "prop": "glasses",
      "palette": "calm",
      "priority": 2,
      "return": "idle",
      "toolIndex": 1
    },
    "Searching": {
      "clip": "searching",
      "expression": "thinking",
      "prop": "magnifier",
      "palette": "calm",
      "priority": 2,
      "return": "idle",
      "toolIndex": 2
    },
    "Writing": {
      "clip": "writing",
      "expression": "thinking",
      "prop": "pencil",
      "palette": "calm",
      "priority": 2,
      "return": "idle",
      "toolIndex": 3
    },
    "Running": {
      "clip": "running",
      "expression": "thinking",
      "prop": "dust",
      "palette": "calm",
      "priority": 2,
      "return": "idle",
      "toolIndex": 4
    },
    "Testing": {
      "clip": "testing",
      "expression": "oops",
      "prop": "ellipsis",
      "palette": "calm",
      "priority": 2,
      "return": "idle",
      "toolIndex": 5
    },
    "Installing": {
      "clip": "installing",
      "expression": "neutral",
      "prop": "ellipsis",
      "palette": "calm",
      "priority": 2,
      "return": "idle",
      "toolIndex": 6
    },
    "Committing": {
      "clip": "committing",
      "expression": "happy",
      "prop": "check",
      "palette": "calm",
      "priority": 3,
      "return": "idle",
      "toolIndex": 7
    },
    "Asking": {
      "clip": "asking",
      "expression": "thinking",
      "prop": "question",
      "palette": "calm",
      "priority": 3,
      "return": "idle",
      "toolIndex": 0
    },
    "Waiting": {
      "clip": "waiting",
      "expression": "neutral",
      "prop": "ellipsis",
      "palette": "calm",
      "priority": 1,
      "return": "idle",
      "toolIndex": 0
    },
    "Fetching": {
      "clip": "fetching",
      "expression": "thinking",
      "prop": "telescope",
      "palette": "calm",
      "priority": 2,
      "return": "idle",
      "toolIndex": 8
    },
    "Planning": {
      "clip": "planning",
      "expression": "thinking",
      "prop": "checklist",
      "palette": "calm",
      "priority": 2,
      "return": "idle",
      "toolIndex": 9
    },
    "Idea": {
      "clip": "react",
      "expression": "excited",
      "prop": "idea",
      "palette": "calm",
      "priority": 4,
      "return": "idle",
      "toolIndex": 0
    }
  },
  "stateMachineGraph": {
    "layers": [
      {
        "name": "Body/Mood",
        "driver": "mood (number 0..7)",
        "behaviour": "a state per expression (or one face artboard with the eyes/mouth/brows swapped by the mood value); blend transitions for a soft change"
      },
      {
        "name": "Tool",
        "driver": "tool (number 0..9)",
        "behaviour": "a tool-gag pose per category (0=none → hidden); props per TOOLS"
      },
      {
        "name": "OneShots",
        "driver": "triggers",
        "behaviour": "react/win/error/compact/wake fire transient timelines that auto-return (recovery, never stuck)"
      }
    ],
    "dataBinds": [
      "fullness (0..100) → body Y-scale (swell) AND cross-fade calm→tired palette (the signature)",
      "moodLevel (-100..100) → a cool \"stressed\" tint floor / warm \"up\" lift",
      "reduceMotion (bool) → reduce timeline amplitude",
      "birds (0..5) → show N orbiting sub-agent birds (nested artboard, count-driven)",
      "sleeping (bool) → curled-down idle + Z's"
    ]
  },
  "timingBudgets": {
    "idle": "2–4 frames ~6fps, randomized blink",
    "reactions": "3–5 frames anticipation→extreme→settle",
    "propsPopIn": "2 frames scale"
  },
  "notes": "Faithful to the existing pixel library; can be pixel-look or vector. The daemon drives the inputs above via lib/rive/driver.mjs — nothing else to wire."
}
